MANIFEST.in
README.md
setup.py
django_testdriver/JsTestDriver-1.3.5.jar
django_testdriver/__init__.py
django_testdriver/models.py
django_testdriver/settings.py
django_testdriver/urls.py
django_testdriver/utils.py
django_testdriver/views.py
django_testdriver.egg-info/PKG-INFO
django_testdriver.egg-info/SOURCES.txt
django_testdriver.egg-info/dependency_links.txt
django_testdriver.egg-info/requires.txt
django_testdriver.egg-info/top_level.txt
django_testdriver/example/jsTestDriver.conf
django_testdriver/example/js/libs/JasmineAdapter.js
django_testdriver/example/js/libs/jasmine-html.js
django_testdriver/example/js/libs/jasmine-jquery-1.3.1.js
django_testdriver/example/js/libs/jasmine.js
django_testdriver/example/js/libs/jquery-1.10.1.min.js
django_testdriver/example/js/tests/setup.js
django_testdriver/example/js/tests/sidebar.js
django_testdriver/example/js/tests/fixtures/sidebar.html
django_testdriver/example/js/tests/fixtures/test.json
django_testdriver/example/js/tests/output/TEST-Firefox_200_Mac_OS.sidebaraloaded.xml
django_testdriver/example/js/tests/output/jsTestDriver.conf-coverage.dat
django_testdriver/example/js/tests/plugins/coverage.jar
django_testdriver/management/__init__.py
django_testdriver/management/commands/__init__.py
django_testdriver/management/commands/jstestdriver.py
django_testdriver/static/css/jasmine.css
django_testdriver/templates/404.html
django_testdriver/templates/django_testdriver/base.html
django_testdriver/tests/__init__.py
django_testdriver/tests/views.py