Metadata-Version: 1.1
Name: django-testdriver
Version: 0.3
Summary: A custom JsTestDriver spec runner etc.
Home-page: http://github.com/spenoir/django_testdriver
Author: spenoir
Author-email: aspence1@gmail.com
License: UNKNOWN
Platform: UNKNOWN
Classifier: Environment :: Web Environment
Classifier: Framework :: Django
Classifier: Intended Audience :: Developers
Classifier: License :: OSI Approved :: BSD License
Classifier: Operating System :: OS Independent
Classifier: Programming Language :: Python :: 2.7
Classifier: Topic :: Internet :: WWW/HTTP
